[
    {
        "block_hash": "39331a6a2ea1cf31a5014b2a7c9e8dfad82df0b0666e81ce04cf8173cc5aed3e",
        "previous_block_hash": "0",
        "transaction_list": [
            "Genesis Block"
        ]
    },
    {
        "previous_block_hash": "39331a6a2ea1cf31a5014b2a7c9e8dfad82df0b0666e81ce04cf8173cc5aed3e",
        "time": "2024-06-23|13:33:00.235",
        "status": "Valide",
        "produit": "Fer",
        "current_place": "Chalons-en-Champagne",
        "destination": "Reims",
        "packages_total_number": "2",
        "packages_total_weight": "400kg",
        "package_id": "972972978",
        "product_detail": "ceci est un  detail",
        "product_family": "Metal",
        "product_current_owner": "Moi",
        "product_origin_country": "Africa",
        "product_origin_producer": "Jupiter",
        "block_hash": "11fbf7c579ccf5f6145ca1cc31e4933bded1e11901181220d9ceceb146efbf64"
    },
    {
        "previous_block_hash": "11fbf7c579ccf5f6145ca1cc31e4933bded1e11901181220d9ceceb146efbf64",
        "time": "2024-06-23|13:33:03.009",
        "status": "Valide",
        "produit": "Fer",
        "current_place": "Chalons-en-Champagne",
        "destination": "Reims",
        "packages_total_number": "2",
        "packages_total_weight": "400kg",
        "package_id": "972972978",
        "product_detail": "ceci est un  detail",
        "product_family": "Metal",
        "product_current_owner": "Moi",
        "product_origin_country": "Africa",
        "product_origin_producer": "Jupiter",
        "block_hash": "557234343466bd98409ed9c863405d4a057300b2a3e9deddfda52cbdb8dcf495"
    },
    {
        "previous_block_hash": "557234343466bd98409ed9c863405d4a057300b2a3e9deddfda52cbdb8dcf495",
        "time": "2024-07-09|19:36:07.643",
        "status": "Valide",
        "produit": "Fer",
        "current_place": "Chalons-en-Champagne",
        "destination": "Reims",
        "packages_total_number": "2",
        "packages_total_weight": "400kg",
        "package_id": "9729729713",
        "product_detail": "ceci est un test3",
        "product_family": "Metal",
        "product_current_owner": "Moi",
        "product_origin_country": "Africa",
        "product_origin_producer": "Jupiter",
        "block_hash": "cd52474db610fe42f59c14fa0517437ae860644fbfa1111a8a2069cf194f4d14"
    },
    {
        "previous_block_hash": "cd52474db610fe42f59c14fa0517437ae860644fbfa1111a8a2069cf194f4d14",
        "time": "2024-07-12|19:50:01.168",
        "status": "Valide",
        "produit": "Fer",
        "current_place": "Chalons-en-Champagne",
        "destination": "Reims",
        "packages_total_number": "2",
        "packages_total_weight": "400kg",
        "package_id": "9729729713",
        "product_detail": "ceci est un test3",
        "product_family": "Metal",
        "product_current_owner": "Moi",
        "product_origin_country": "Africa",
        "product_origin_producer": "Jupiter",
        "block_hash": "bb68dd00efa1023e16947adc925cee06542f46612539c5e323c3057f1a85dcf3"
    },
    {
        "previous_block_hash": "bb68dd00efa1023e16947adc925cee06542f46612539c5e323c3057f1a85dcf3",
        "time": "2024-07-12|19:51:19.716",
        "status": "Valide",
        "produit": "Fer",
        "current_place": "Chalons-en-Champagne",
        "destination": "Reims",
        "packages_total_number": "2",
        "packages_total_weight": "400kg",
        "package_id": "9729729713",
        "product_detail": "ceci est un test3",
        "product_family": "Metal",
        "product_current_owner": "Moi",
        "product_origin_country": "Africa",
        "product_origin_producer": "Jupiter",
        "block_hash": "ae05d4bd151d6554f085d5a4bd8972861b5bf465b03c9c14f927061a4e4e0401"
    },
    {
        "previous_block_hash": "ae05d4bd151d6554f085d5a4bd8972861b5bf465b03c9c14f927061a4e4e0401",
        "time": "2024-07-14|13:45:04.162",
        "status": "Valide",
        "produit": "Fer",
        "current_place": "Chalons-en-Champagne",
        "destination": "Reims",
        "packages_total_number": "2",
        "packages_total_weight": "400kg",
        "package_id": "9729729713",
        "product_detail": "ceci est un test3",
        "product_family": "Metal",
        "product_current_owner": "Moi",
        "product_origin_country": "Africa",
        "product_origin_producer": "Jupiter",
        "block_hash": "2d027d90d9cd11a828867aeda6639063809623d294ffa2fb27629c709a9b6b23"
    },
    {
        "previous_block_hash": "2d027d90d9cd11a828867aeda6639063809623d294ffa2fb27629c709a9b6b23",
        "time": "2024-07-14|13:50:43.112",
        "status": "Valide",
        "produit": "Fer",
        "current_place": "Chalons-en-Champagne",
        "destination": "Reims",
        "packages_total_number": "2",
        "packages_total_weight": "400kg",
        "package_id": "9729729713",
        "product_detail": "ceci est un test3",
        "product_family": "Metal",
        "product_current_owner": "Moi",
        "product_origin_country": "Africa",
        "product_origin_producer": "Jupiter",
        "block_hash": "ecb7826e68ad08e39182143a76dde2a30014511355dd60165f3ac8fb2ca466df"
    },
    {
        "previous_block_hash": "ecb7826e68ad08e39182143a76dde2a30014511355dd60165f3ac8fb2ca466df",
        "time": "2024-07-14|14:00:23.952",
        "status": "Valide",
        "produit": "Fer",
        "current_place": "Chalons-en-Champagne",
        "destination": "Reims",
        "packages_total_number": "2",
        "packages_total_weight": "400kg",
        "package_id": "9729729713",
        "product_detail": "ceci est un test3",
        "product_family": "Metal",
        "product_current_owner": "Moi",
        "product_origin_country": "Africa",
        "product_origin_producer": "Jupiter",
        "block_hash": "03ca5b260f3fef853b725232e02ef3355e5234e3f67095a3fb9f416092ef5934"
    },
    {
        "previous_block_hash": "03ca5b260f3fef853b725232e02ef3355e5234e3f67095a3fb9f416092ef5934",
        "time": "2024-07-14|14:17:15.852",
        "status": "Valide",
        "produit": "Fer",
        "current_place": "Chalons-en-Champagne",
        "destination": "Reims",
        "packages_total_number": "2",
        "packages_total_weight": "400kg",
        "package_id": "9729729713",
        "product_detail": "ceci est un test3",
        "product_family": "Metal",
        "product_current_owner": "Moi",
        "product_origin_country": "Africa",
        "product_origin_producer": "Jupiter",
        "block_hash": "4a37460477c9fad076bd3455c20814526b100a1a9cb957d4de557a7425ccfd35"
    },
    {
        "previous_block_hash": "4a37460477c9fad076bd3455c20814526b100a1a9cb957d4de557a7425ccfd35",
        "time": "2024-07-14|14:23:08.287",
        "status": "Valide",
        "produit": "Fer",
        "current_place": "Chalons-en-Champagne",
        "destination": "Reims",
        "packages_total_number": "2",
        "packages_total_weight": "400kg",
        "package_id": "9729729713",
        "product_detail": "ceci est un test3",
        "product_family": "Metal",
        "product_current_owner": "Moi",
        "product_origin_country": "Africa",
        "product_origin_producer": "Jupiter",
        "block_hash": "02e957e1f0094ebcf23ce765b1e74394aba2f1a6054bc09f4953e15f1f61d051"
    },
    {
        "previous_block_hash": "02e957e1f0094ebcf23ce765b1e74394aba2f1a6054bc09f4953e15f1f61d051",
        "time": "2024-07-14|14:25:30.849",
        "status": "Valide",
        "produit": "Fer",
        "current_place": "Chalons-en-Champagne",
        "destination": "Reims",
        "packages_total_number": "2",
        "packages_total_weight": "400kg",
        "package_id": "9729729713",
        "product_detail": "ceci est un test3",
        "product_family": "Metal",
        "product_current_owner": "Moi",
        "product_origin_country": "Africa",
        "product_origin_producer": "Jupiter",
        "block_hash": "2377a75dbc5c77cce4fafcef1ec1f23d5dd0dd8ca60302f3b5ea883e5fc26929"
    },
    {
        "previous_block_hash": "2377a75dbc5c77cce4fafcef1ec1f23d5dd0dd8ca60302f3b5ea883e5fc26929",
        "time": "2024-07-14|14:27:17.784",
        "status": "Valide",
        "produit": "Fer",
        "current_place": "Chalons-en-Champagne",
        "destination": "Reims",
        "packages_total_number": "2",
        "packages_total_weight": "400kg",
        "package_id": "9729729713",
        "product_detail": "ceci est un test3",
        "product_family": "Metal",
        "product_current_owner": "Moi",
        "product_origin_country": "Africa",
        "product_origin_producer": "Jupiter",
        "block_hash": "b2a16b7388301ac2348ccd01136745a845ec6b20760c2d930328d50f88243770"
    },
    {
        "previous_block_hash": "b2a16b7388301ac2348ccd01136745a845ec6b20760c2d930328d50f88243770",
        "time": "2024-07-14|14:27:31.312",
        "status": "Valide",
        "produit": "Fer",
        "current_place": "Chalons-en-Champagne",
        "destination": "Reims",
        "packages_total_number": "2",
        "packages_total_weight": "400kg",
        "package_id": "9729729713",
        "product_detail": "ceci est un test3",
        "product_family": "Metal",
        "product_current_owner": "Moi",
        "product_origin_country": "Africa",
        "product_origin_producer": "Jupiter",
        "block_hash": "e340660e0155f1b87bc615eee48a7cb96726ca1bc9c48245d6d89b4d3f2521e4"
    },
    {
        "previous_block_hash": "e340660e0155f1b87bc615eee48a7cb96726ca1bc9c48245d6d89b4d3f2521e4",
        "time": "2024-07-14|14:27:48.905",
        "status": "Valide",
        "produit": "Fer",
        "current_place": "Chalons-en-Champagne",
        "destination": "Reims",
        "packages_total_number": "2",
        "packages_total_weight": "400kg",
        "package_id": "9729729713",
        "product_detail": "ceci est un test3",
        "product_family": "Metal",
        "product_current_owner": "Moi",
        "product_origin_country": "Africa",
        "product_origin_producer": "Jupiter",
        "block_hash": "9101c16c84f69320ca7939538d16a9eef7db0452f1fdb7faed4f52c038a34447"
    },
    {
        "previous_block_hash": "9101c16c84f69320ca7939538d16a9eef7db0452f1fdb7faed4f52c038a34447",
        "time": "2024-07-14|14:28:06.484",
        "status": "Valide",
        "produit": "Fer",
        "current_place": "Chalons-en-Champagne",
        "destination": "Reims",
        "packages_total_number": "2",
        "packages_total_weight": "400kg",
        "package_id": "9729729713",
        "product_detail": "ceci est un test3",
        "product_family": "Metal",
        "product_current_owner": "Moi",
        "product_origin_country": "Africa",
        "product_origin_producer": "Jupiter",
        "block_hash": "a02a4d866bbd5246319e4ea826fe848208909816ab4528468d6ff639cca86f72"
    },
    {
        "previous_block_hash": "a02a4d866bbd5246319e4ea826fe848208909816ab4528468d6ff639cca86f72",
        "time": "2024-07-14|14:28:26.712",
        "status": "Valide",
        "produit": "Fer",
        "current_place": "Chalons-en-Champagne",
        "destination": "Reims",
        "packages_total_number": "2",
        "packages_total_weight": "400kg",
        "package_id": "9729729713",
        "product_detail": "ceci est un test3",
        "product_family": "Metal",
        "product_current_owner": "Moi",
        "product_origin_country": "Africa",
        "product_origin_producer": "Jupiter",
        "block_hash": "8b869f809a30f54f691c8ea5c52611671ba50dc39ab57d7bdad1824f1a018586"
    },
    {
        "previous_block_hash": "8b869f809a30f54f691c8ea5c52611671ba50dc39ab57d7bdad1824f1a018586",
        "time": "2024-07-14|14:29:04.640",
        "status": "Valide",
        "produit": "Fer",
        "current_place": "Chalons-en-Champagne",
        "destination": "Reims",
        "packages_total_number": "2",
        "packages_total_weight": "400kg",
        "package_id": "9729729713",
        "product_detail": "ceci est un test3",
        "product_family": "Metal",
        "product_current_owner": "Moi",
        "product_origin_country": "Africa",
        "product_origin_producer": "Jupiter",
        "block_hash": "a6a93df60125099fb931779508a04d6ea36cf5839e1849096df2a56b249e09b2"
    },
    {
        "previous_block_hash": "a6a93df60125099fb931779508a04d6ea36cf5839e1849096df2a56b249e09b2",
        "time": "2024-07-14|14:31:03.725",
        "status": "Valide",
        "produit": "Fer",
        "current_place": "Chalons-en-Champagne",
        "destination": "Reims",
        "packages_total_number": "2",
        "packages_total_weight": "400kg",
        "package_id": "9729729713",
        "product_detail": "ceci est un test3",
        "product_family": "Metal",
        "product_current_owner": "Moi",
        "product_origin_country": "Africa",
        "product_origin_producer": "Jupiter",
        "block_hash": "5a4c5c377d8f222ab01bbe7e723ba44648b33a8f8ef7372c62fe50dfc18dc64f"
    },
    {
        "previous_block_hash": "5a4c5c377d8f222ab01bbe7e723ba44648b33a8f8ef7372c62fe50dfc18dc64f",
        "time": "2024-07-14|14:31:26.725",
        "status": "Valide",
        "produit": "Fer",
        "current_place": "Chalons-en-Champagne",
        "destination": "Reims",
        "packages_total_number": "2",
        "packages_total_weight": "400kg",
        "package_id": "9729729713",
        "product_detail": "ceci est un test3",
        "product_family": "Metal",
        "product_current_owner": "Moi",
        "product_origin_country": "Africa",
        "product_origin_producer": "Jupiter",
        "block_hash": "c7f08219a3de1024c6c44b510f808584ef84f588a3f165549f8224f5a017bd49"
    },
    {
        "previous_block_hash": "c7f08219a3de1024c6c44b510f808584ef84f588a3f165549f8224f5a017bd49",
        "time": "2024-07-14|14:31:59.020",
        "status": "Valide",
        "produit": "Fer",
        "current_place": "Chalons-en-Champagne",
        "destination": "Reims",
        "packages_total_number": "2",
        "packages_total_weight": "400kg",
        "package_id": "9729729713",
        "product_detail": "ceci est un test3",
        "product_family": "Metal",
        "product_current_owner": "Moi",
        "product_origin_country": "Africa",
        "product_origin_producer": "Jupiter",
        "block_hash": "324fd802316767210e365545798b98a318c55464d95cc409e8b9f94975aeb839"
    },
    {
        "previous_block_hash": "324fd802316767210e365545798b98a318c55464d95cc409e8b9f94975aeb839",
        "time": "2024-07-14|14:35:46.745",
        "status": "Valide",
        "produit": "Fer",
        "current_place": "Chalons-en-Champagne",
        "destination": "Reims",
        "packages_total_number": "2",
        "packages_total_weight": "400kg",
        "package_id": "9729729713",
        "product_detail": "ceci est un test3",
        "product_family": "Metal",
        "product_current_owner": "Moi",
        "product_origin_country": "Africa",
        "product_origin_producer": "Jupiter",
        "block_hash": "58aba48c0284c89e7a545fe9f2f3e93217b0bd285039e8103ef00fd65ff6b28e"
    },
    {
        "previous_block_hash": "58aba48c0284c89e7a545fe9f2f3e93217b0bd285039e8103ef00fd65ff6b28e",
        "time": "2024-07-14|14:36:05.093",
        "status": "Valide",
        "produit": "Fer",
        "current_place": "Chalons-en-Champagne",
        "destination": "Reims",
        "packages_total_number": "2",
        "packages_total_weight": "400kg",
        "package_id": "9729729713",
        "product_detail": "ceci est un test3",
        "product_family": "Metal",
        "product_current_owner": "Moi",
        "product_origin_country": "Africa",
        "product_origin_producer": "Jupiter",
        "block_hash": "9d0fbf63ce55cab33ddc3257bbcc77b89904c0674187565bd69f44fe382147e3"
    },
    {
        "previous_block_hash": "9d0fbf63ce55cab33ddc3257bbcc77b89904c0674187565bd69f44fe382147e3",
        "time": "2024-07-14|14:36:15.159",
        "status": "Valide",
        "produit": "Fer",
        "current_place": "Chalons-en-Champagne",
        "destination": "Reims",
        "packages_total_number": "2",
        "packages_total_weight": "400kg",
        "package_id": "9729729713",
        "product_detail": "ceci est un test3",
        "product_family": "Metal",
        "product_current_owner": "Moi",
        "product_origin_country": "Africa",
        "product_origin_producer": "Jupiter",
        "block_hash": "e16d4767119e9a4008494216fabb197ec3b77491bcc09ce9154acc2308371c9b"
    },
    {
        "previous_block_hash": "e16d4767119e9a4008494216fabb197ec3b77491bcc09ce9154acc2308371c9b",
        "time": "2024-07-14|14:37:26.902",
        "status": "Valide",
        "produit": "Fer",
        "current_place": "Chalons-en-Champagne",
        "destination": "Reims",
        "packages_total_number": "2",
        "packages_total_weight": "400kg",
        "package_id": "9729729713",
        "product_detail": "ceci est un test3",
        "product_family": "Metal",
        "product_current_owner": "Moi",
        "product_origin_country": "Africa",
        "product_origin_producer": "Jupiter",
        "block_hash": "256253ccaa890738a6d026e9270d8c49d7ef75d58c1991b680d17138d5376468"
    },
    {
        "previous_block_hash": "256253ccaa890738a6d026e9270d8c49d7ef75d58c1991b680d17138d5376468",
        "time": "2024-07-14|14:39:25.236",
        "status": "Valide",
        "produit": "Fer",
        "current_place": "Chalons-en-Champagne",
        "destination": "Reims",
        "packages_total_number": "2",
        "packages_total_weight": "400kg",
        "package_id": "9729729713",
        "product_detail": "ceci est un test3",
        "product_family": "Metal",
        "product_current_owner": "Moi",
        "product_origin_country": "Africa",
        "product_origin_producer": "Jupiter",
        "block_hash": "642901211e405dd224fe8cf3c18112ce68176fb8dab1cf4af17e8746ad8f2d40"
    },
    {
        "previous_block_hash": "642901211e405dd224fe8cf3c18112ce68176fb8dab1cf4af17e8746ad8f2d40",
        "time": "2024-07-14|14:39:51.956",
        "status": "Valide",
        "produit": "Fer",
        "current_place": "Chalons-en-Champagne",
        "destination": "Reims",
        "packages_total_number": "2",
        "packages_total_weight": "400kg",
        "package_id": "9729729713",
        "product_detail": "ceci est un test3",
        "product_family": "Metal",
        "product_current_owner": "Moi",
        "product_origin_country": "Africa",
        "product_origin_producer": "Jupiter",
        "block_hash": "bf118e3ca924febd139dd2e12ab7a37f9d978988ac61c5bf591a4b462db9eab6"
    },
    {
        "previous_block_hash": "bf118e3ca924febd139dd2e12ab7a37f9d978988ac61c5bf591a4b462db9eab6",
        "time": "2024-07-14|14:40:14.593",
        "status": "Valide",
        "produit": "Fer",
        "current_place": "Chalons-en-Champagne",
        "destination": "Reims",
        "packages_total_number": "2",
        "packages_total_weight": "400kg",
        "package_id": "9729729713",
        "product_detail": "ceci est un test3",
        "product_family": "Metal",
        "product_current_owner": "Moi",
        "product_origin_country": "Africa",
        "product_origin_producer": "Jupiter",
        "block_hash": "e91939bc483b3ce4cc8adc6f97723202ff71e4459fda9a06ed2ee4831299bc14"
    },
    {
        "previous_block_hash": "e91939bc483b3ce4cc8adc6f97723202ff71e4459fda9a06ed2ee4831299bc14",
        "time": "2024-07-14|14:42:05.652",
        "status": "Valide",
        "produit": "Fer",
        "current_place": "Chalons-en-Champagne",
        "destination": "Reims",
        "packages_total_number": "2",
        "packages_total_weight": "400kg",
        "package_id": "9729729713",
        "product_detail": "ceci est un test3",
        "product_family": "Metal",
        "product_current_owner": "Moi",
        "product_origin_country": "Africa",
        "product_origin_producer": "Jupiter",
        "block_hash": "dbf2ec638d74b3333adee8f9ab8e71f4eea2cd5668546e1ff0aa86ee714a35f4"
    },
    {
        "previous_block_hash": "dbf2ec638d74b3333adee8f9ab8e71f4eea2cd5668546e1ff0aa86ee714a35f4",
        "time": "2024-07-14|14:44:37.666",
        "status": "Valide",
        "produit": "Fer",
        "current_place": "Chalons-en-Champagne",
        "destination": "Reims",
        "packages_total_number": "2",
        "packages_total_weight": "400kg",
        "package_id": "9729729713",
        "product_detail": "ceci est un test3",
        "product_family": "Metal",
        "product_current_owner": "Moi",
        "product_origin_country": "Africa",
        "product_origin_producer": "Jupiter",
        "block_hash": "a04f2611c61c4ea6e2719c53da6de0fd5a72235b5f742030668962a3fa7dff1b"
    },
    {
        "previous_block_hash": "a04f2611c61c4ea6e2719c53da6de0fd5a72235b5f742030668962a3fa7dff1b",
        "time": "2024-07-14|14:45:55.438",
        "status": "Valide",
        "produit": "Fer",
        "current_place": "Chalons-en-Champagne",
        "destination": "Reims",
        "packages_total_number": "2",
        "packages_total_weight": "400kg",
        "package_id": "9729729713",
        "product_detail": "ceci est un test3",
        "product_family": "Metal",
        "product_current_owner": "Moi",
        "product_origin_country": "Africa",
        "product_origin_producer": "Jupiter",
        "block_hash": "d93656a681d4f0080126ca865339044549fef6b7ecdc17402401afab101c7610"
    },
    {
        "previous_block_hash": "d93656a681d4f0080126ca865339044549fef6b7ecdc17402401afab101c7610",
        "time": "2024-07-14|14:46:20.082",
        "status": "Valide",
        "produit": "Fer",
        "current_place": "Chalons-en-Champagne",
        "destination": "Reims",
        "packages_total_number": "2",
        "packages_total_weight": "400kg",
        "package_id": "9729729713",
        "product_detail": "ceci est un test3",
        "product_family": "Metal",
        "product_current_owner": "Moi",
        "product_origin_country": "Africa",
        "product_origin_producer": "Jupiter",
        "block_hash": "af09976d5f7fd6e6d547b131aefb64490cb83f78bd97e51a8a40e642ea88c54e"
    },
    {
        "previous_block_hash": "af09976d5f7fd6e6d547b131aefb64490cb83f78bd97e51a8a40e642ea88c54e",
        "time": "2024-07-14|14:47:00.320",
        "status": "Valide",
        "produit": "Fer",
        "current_place": "Chalons-en-Champagne",
        "destination": "Reims",
        "packages_total_number": "2",
        "packages_total_weight": "400kg",
        "package_id": "9729729713",
        "product_detail": "ceci est un test3",
        "product_family": "Metal",
        "product_current_owner": "Moi",
        "product_origin_country": "Africa",
        "product_origin_producer": "Jupiter",
        "block_hash": "0886fca3165050e58f111c8860d171e1d8fec3eb14d5ac5d28ed10fdab43caf9"
    },
    {
        "previous_block_hash": "0886fca3165050e58f111c8860d171e1d8fec3eb14d5ac5d28ed10fdab43caf9",
        "time": "2024-07-14|14:50:25.216",
        "status": "Valide",
        "produit": "Fer",
        "current_place": "Chalons-en-Champagne",
        "destination": "Reims",
        "packages_total_number": "2",
        "packages_total_weight": "400kg",
        "package_id": "9729729713",
        "product_detail": "ceci est un test3",
        "product_family": "Metal",
        "product_current_owner": "Moi",
        "product_origin_country": "Africa",
        "product_origin_producer": "Jupiter",
        "block_hash": "f776588b76b30aa7202ce887f0ca213d1d492823db7f14d1078394950d93f28b"
    },
    {
        "previous_block_hash": "f776588b76b30aa7202ce887f0ca213d1d492823db7f14d1078394950d93f28b",
        "time": "2024-07-14|14:50:43.153",
        "status": "Valide",
        "produit": "Fer",
        "current_place": "Chalons-en-Champagne",
        "destination": "Reims",
        "packages_total_number": "2",
        "packages_total_weight": "400kg",
        "package_id": "9729729713",
        "product_detail": "ceci est un test3",
        "product_family": "Metal",
        "product_current_owner": "Moi",
        "product_origin_country": "Africa",
        "product_origin_producer": "Jupiter",
        "block_hash": "e7cb0605492e443201050c3a365ef7221a89571283945301588ac02723fa8d2e"
    },
    {
        "previous_block_hash": "e7cb0605492e443201050c3a365ef7221a89571283945301588ac02723fa8d2e",
        "time": "2024-07-14|14:50:57.645",
        "status": "Valide",
        "produit": "Fer",
        "current_place": "Chalons-en-Champagne",
        "destination": "Reims",
        "packages_total_number": "2",
        "packages_total_weight": "400kg",
        "package_id": "9729729713",
        "product_detail": "ceci est un test3",
        "product_family": "Metal",
        "product_current_owner": "Moi",
        "product_origin_country": "Africa",
        "product_origin_producer": "Jupiter",
        "block_hash": "186462a9eeb03b915a9c218ae6c1ade62b3cc64f33120e917d3a2f52a3650436"
    },
    {
        "previous_block_hash": "186462a9eeb03b915a9c218ae6c1ade62b3cc64f33120e917d3a2f52a3650436",
        "time": "2024-07-14|14:51:53.856",
        "status": "Valide",
        "produit": "Fer",
        "current_place": "Chalons-en-Champagne",
        "destination": "Reims",
        "packages_total_number": "2",
        "packages_total_weight": "400kg",
        "package_id": "9729729713",
        "product_detail": "ceci est un test3",
        "product_family": "Metal",
        "product_current_owner": "Moi",
        "product_origin_country": "Africa",
        "product_origin_producer": "Jupiter",
        "block_hash": "e8e6c53ff745c0e8168fba283529c0a766d1419ad17fd5193d8a05229568482f"
    },
    {
        "previous_block_hash": "e8e6c53ff745c0e8168fba283529c0a766d1419ad17fd5193d8a05229568482f",
        "time": "2024-07-14|14:51:58.540",
        "status": "Valide",
        "produit": "Fer",
        "current_place": "Chalons-en-Champagne",
        "destination": "Reims",
        "packages_total_number": "2",
        "packages_total_weight": "400kg",
        "package_id": "9729729713",
        "product_detail": "ceci est un test3",
        "product_family": "Metal",
        "product_current_owner": "Moi",
        "product_origin_country": "Africa",
        "product_origin_producer": "Jupiter",
        "block_hash": "2ac722317dfd2096233d9dc0cb315b517a6fc3addb0020dfa73d069f86e3f274"
    },
    {
        "previous_block_hash": "2ac722317dfd2096233d9dc0cb315b517a6fc3addb0020dfa73d069f86e3f274",
        "time": "2024-07-14|14:55:27.854",
        "status": "Valide",
        "produit": "Fer",
        "current_place": "Chalons-en-Champagne",
        "destination": "Reims",
        "packages_total_number": "2",
        "packages_total_weight": "400kg",
        "package_id": "9729729713",
        "product_detail": "ceci est un test3",
        "product_family": "Metal",
        "product_current_owner": "Moi",
        "product_origin_country": "Africa",
        "product_origin_producer": "Jupiter",
        "block_hash": "af380a29f11e0f2f3933e002625389e4f6ae919057f9c396a077c52236101db5"
    },
    {
        "previous_block_hash": "af380a29f11e0f2f3933e002625389e4f6ae919057f9c396a077c52236101db5",
        "time": "2024-07-14|14:58:10.898",
        "status": "Valide",
        "produit": "Fer",
        "current_place": "Chalons-en-Champagne",
        "destination": "Reims",
        "packages_total_number": "2",
        "packages_total_weight": "400kg",
        "package_id": "9729729713",
        "product_detail": "ceci est un test3",
        "product_family": "Metal",
        "product_current_owner": "Moi",
        "product_origin_country": "Africa",
        "product_origin_producer": "Jupiter",
        "block_hash": "d053d6fd905cfcf930a4357894a9c474e9367f414120f64a6034737c6adc5487"
    },
    {
        "previous_block_hash": "d053d6fd905cfcf930a4357894a9c474e9367f414120f64a6034737c6adc5487",
        "time": "2024-07-14|14:58:44.799",
        "status": "Valide",
        "produit": "Fer",
        "current_place": "Chalons-en-Champagne",
        "destination": "Reims",
        "packages_total_number": "2",
        "packages_total_weight": "400kg",
        "package_id": "9729729713",
        "product_detail": "ceci est un test3",
        "product_family": "Metal",
        "product_current_owner": "Moi",
        "product_origin_country": "Africa",
        "product_origin_producer": "Jupiter",
        "block_hash": "6e3e9f291c066faf4981bb0c9a4a68e50ad53fa547ef8e765788d44c4ba8e41a"
    },
    {
        "previous_block_hash": "6e3e9f291c066faf4981bb0c9a4a68e50ad53fa547ef8e765788d44c4ba8e41a",
        "time": "2024-07-14|14:59:00.136",
        "status": "Valide",
        "produit": "Fer",
        "current_place": "Chalons-en-Champagne",
        "destination": "Reims",
        "packages_total_number": "2",
        "packages_total_weight": "400kg",
        "package_id": "9729729713",
        "product_detail": "ceci est un test3",
        "product_family": "Metal",
        "product_current_owner": "Moi",
        "product_origin_country": "Africa",
        "product_origin_producer": "Jupiter",
        "block_hash": "ac6534c127fa807a85c9802c76f4a1548207be89cce7ba5bc485d074dd0c2da2"
    },
    {
        "previous_block_hash": "ac6534c127fa807a85c9802c76f4a1548207be89cce7ba5bc485d074dd0c2da2",
        "time": "2024-07-14|14:59:20.349",
        "status": "Valide",
        "produit": "Fer",
        "current_place": "Chalons-en-Champagne",
        "destination": "Reims",
        "packages_total_number": "2",
        "packages_total_weight": "400kg",
        "package_id": "9729729713",
        "product_detail": "ceci est un test3",
        "product_family": "Metal",
        "product_current_owner": "Moi",
        "product_origin_country": "Africa",
        "product_origin_producer": "Jupiter",
        "block_hash": "c12cde0955a383bf39ee4fbd1d1f4326c1cee0135ab4a8f0c6309b5affca9d32"
    },
    {
        "previous_block_hash": "c12cde0955a383bf39ee4fbd1d1f4326c1cee0135ab4a8f0c6309b5affca9d32",
        "time": "2024-07-14|15:01:27.308",
        "status": "Valide",
        "produit": "Fer",
        "current_place": "Chalons-en-Champagne",
        "destination": "Reims",
        "packages_total_number": "2",
        "packages_total_weight": "400kg",
        "package_id": "9729729713",
        "product_detail": "ceci est un test3",
        "product_family": "Metal",
        "product_current_owner": "Moi",
        "product_origin_country": "Africa",
        "product_origin_producer": "Jupiter",
        "block_hash": "5cc5791fd54332393b2570e52b317effd41d8c8a708e33e1f4c5890c699533ad"
    },
    {
        "previous_block_hash": "5cc5791fd54332393b2570e52b317effd41d8c8a708e33e1f4c5890c699533ad",
        "time": "2024-07-14|15:02:14.516",
        "status": "Valide",
        "produit": "Fer",
        "current_place": "Chalons-en-Champagne",
        "destination": "Reims",
        "packages_total_number": "2",
        "packages_total_weight": "400kg",
        "package_id": "9729729713",
        "product_detail": "ceci est un test3",
        "product_family": "Metal",
        "product_current_owner": "Moi",
        "product_origin_country": "Africa",
        "product_origin_producer": "Jupiter",
        "block_hash": "e970d667fb70cbb07b055c5a8bc0c083135483ba228c133912cf21a1b8f3239b"
    },
    {
        "previous_block_hash": "e970d667fb70cbb07b055c5a8bc0c083135483ba228c133912cf21a1b8f3239b",
        "time": "2024-07-14|15:04:38.763",
        "status": "Valide",
        "produit": "Fer",
        "current_place": "Chalons-en-Champagne",
        "destination": "Reims",
        "packages_total_number": "2",
        "packages_total_weight": "400kg",
        "package_id": "9729729713",
        "product_detail": "ceci est un test3",
        "product_family": "Metal",
        "product_current_owner": "Moi",
        "product_origin_country": "Africa",
        "product_origin_producer": "Jupiter",
        "block_hash": "fd6631a27e6b15f409feb09febb5f4f9d8cd50fe6e36134624acdbb44428f651"
    },
    {
        "previous_block_hash": "fd6631a27e6b15f409feb09febb5f4f9d8cd50fe6e36134624acdbb44428f651",
        "time": "2024-07-14|15:04:52.245",
        "status": "Valide",
        "produit": "Fer",
        "current_place": "Chalons-en-Champagne",
        "destination": "Reims",
        "packages_total_number": "2",
        "packages_total_weight": "400kg",
        "package_id": "9729729713",
        "product_detail": "ceci est un test3",
        "product_family": "Metal",
        "product_current_owner": "Moi",
        "product_origin_country": "Africa",
        "product_origin_producer": "Jupiter",
        "block_hash": "06704460b891bf8875fbde9639c53bcd12bcd4ccecde56fea9918f7309bd325a"
    },
    {
        "previous_block_hash": "06704460b891bf8875fbde9639c53bcd12bcd4ccecde56fea9918f7309bd325a",
        "time": "2024-07-14|15:08:11.158",
        "status": "Valide",
        "produit": "Fer",
        "current_place": "Chalons-en-Champagne",
        "destination": "Reims",
        "packages_total_number": "2",
        "packages_total_weight": "400kg",
        "package_id": "9729729713",
        "product_detail": "ceci est un test3",
        "product_family": "Metal",
        "product_current_owner": "Moi",
        "product_origin_country": "Africa",
        "product_origin_producer": "Jupiter",
        "block_hash": "07d5777f490b067e8c16d30110043babaa90654456818226ce2a17d869972ab9"
    },
    {
        "previous_block_hash": "07d5777f490b067e8c16d30110043babaa90654456818226ce2a17d869972ab9",
        "time": "2024-07-14|15:08:18.234",
        "status": "Valide",
        "produit": "Fer",
        "current_place": "Chalons-en-Champagne",
        "destination": "Reims",
        "packages_total_number": "2",
        "packages_total_weight": "400kg",
        "package_id": "9729729713",
        "product_detail": "ceci est un test3",
        "product_family": "Metal",
        "product_current_owner": "Moi",
        "product_origin_country": "Africa",
        "product_origin_producer": "Jupiter",
        "block_hash": "7ee86ec8097fcebe3ee6c600b629a6a435da9f9454efcd720b4dff370205e718"
    },
    {
        "previous_block_hash": "7ee86ec8097fcebe3ee6c600b629a6a435da9f9454efcd720b4dff370205e718",
        "time": "2024-07-14|15:08:38.453",
        "status": "Valide",
        "produit": "Fer",
        "current_place": "Chalons-en-Champagne",
        "destination": "Reims",
        "packages_total_number": "2",
        "packages_total_weight": "400kg",
        "package_id": "9729729713",
        "product_detail": "ceci est un test3",
        "product_family": "Metal",
        "product_current_owner": "Moi",
        "product_origin_country": "Africa",
        "product_origin_producer": "Jupiter",
        "block_hash": "6f0cb52a0d1cc80484ffdb90ba585d6765de354622dacd3cad083d77e1a21954"
    },
    {
        "previous_block_hash": "6f0cb52a0d1cc80484ffdb90ba585d6765de354622dacd3cad083d77e1a21954",
        "time": "2024-07-14|15:08:59.449",
        "status": "Valide",
        "produit": "Fer",
        "current_place": "Chalons-en-Champagne",
        "destination": "Reims",
        "packages_total_number": "2",
        "packages_total_weight": "400kg",
        "package_id": "9729729713",
        "product_detail": "ceci est un test3",
        "product_family": "Metal",
        "product_current_owner": "Moi",
        "product_origin_country": "Africa",
        "product_origin_producer": "Jupiter",
        "block_hash": "6d3731f9349a8c5e8120d2abf6712488651348502e0a50ccb8b7837b433b9f03"
    },
    {
        "previous_block_hash": "6d3731f9349a8c5e8120d2abf6712488651348502e0a50ccb8b7837b433b9f03",
        "time": "2024-07-14|15:12:16.749",
        "status": "Valide",
        "produit": "Fer",
        "current_place": "Chalons-en-Champagne",
        "destination": "Reims",
        "packages_total_number": "2",
        "packages_total_weight": "400kg",
        "package_id": "9729729713",
        "product_detail": "ceci est un test3",
        "product_family": "Metal",
        "product_current_owner": "Moi",
        "product_origin_country": "Africa",
        "product_origin_producer": "Jupiter",
        "block_hash": "3d1716a33841fb19d4597debf5fff31b37140bc43560008874ff21a063df18c8"
    },
    {
        "previous_block_hash": "3d1716a33841fb19d4597debf5fff31b37140bc43560008874ff21a063df18c8",
        "time": "2024-07-14|15:34:10.444",
        "status": "Valide",
        "produit": "Fer",
        "current_place": "Chalons-en-Champagne",
        "destination": "Reims",
        "packages_total_number": "2",
        "packages_total_weight": "400kg",
        "package_id": "9729729713",
        "product_detail": "ceci est un test3",
        "product_family": "Metal",
        "product_current_owner": "Moi",
        "product_origin_country": "Africa",
        "product_origin_producer": "Jupiter",
        "block_hash": "efb2cf9e6098e3b0776b0010500e2f0f3d2a35ba8921ee20b0e4358158f8906c"
    },
    {
        "previous_block_hash": "efb2cf9e6098e3b0776b0010500e2f0f3d2a35ba8921ee20b0e4358158f8906c",
        "time": "2024-07-14|15:35:14.918",
        "status": "Valide",
        "produit": "Fer",
        "current_place": "Chalons-en-Champagne",
        "destination": "Reims",
        "packages_total_number": "2",
        "packages_total_weight": "400kg",
        "package_id": "9729729713",
        "product_detail": "ceci est un test3",
        "product_family": "Metal",
        "product_current_owner": "Moi",
        "product_origin_country": "Africa",
        "product_origin_producer": "Jupiter",
        "block_hash": "c9ad463560f074b420e27fbad9645b975b104cf4affebd9d77a73dde53d0a842"
    },
    {
        "previous_block_hash": "c9ad463560f074b420e27fbad9645b975b104cf4affebd9d77a73dde53d0a842",
        "time": "2024-07-14|15:37:27.113",
        "status": "Valide",
        "produit": "Fer",
        "current_place": "Chalons-en-Champagne",
        "destination": "Reims",
        "packages_total_number": "2",
        "packages_total_weight": "400kg",
        "package_id": "9729729713",
        "product_detail": "ceci est un test3",
        "product_family": "Metal",
        "product_current_owner": "Moi",
        "product_origin_country": "Africa",
        "product_origin_producer": "Jupiter",
        "block_hash": "9e32726d8848722ac12df4aab802ded030016bd0d7c93398dd1112e09a4d80f0"
    },
    {
        "previous_block_hash": "9e32726d8848722ac12df4aab802ded030016bd0d7c93398dd1112e09a4d80f0",
        "time": "2024-07-14|15:37:44.279",
        "status": "Valide",
        "produit": "Fer",
        "current_place": "Chalons-en-Champagne",
        "destination": "Reims",
        "packages_total_number": "2",
        "packages_total_weight": "400kg",
        "package_id": "9729729713",
        "product_detail": "ceci est un test3",
        "product_family": "Metal",
        "product_current_owner": "Moi",
        "product_origin_country": "Africa",
        "product_origin_producer": "Jupiter",
        "block_hash": "2c80083d0f4687086df95da7f7beeaa94a24219479e07952d4fb3350ee101007"
    },
    {
        "previous_block_hash": "2c80083d0f4687086df95da7f7beeaa94a24219479e07952d4fb3350ee101007",
        "time": "2024-07-14|15:38:14.134",
        "status": "Valide",
        "produit": "Fer",
        "current_place": "Chalons-en-Champagne",
        "destination": "Reims",
        "packages_total_number": "2",
        "packages_total_weight": "400kg",
        "package_id": "9729729713",
        "product_detail": "ceci est un test3",
        "product_family": "Metal",
        "product_current_owner": "Moi",
        "product_origin_country": "Africa",
        "product_origin_producer": "Jupiter",
        "block_hash": "ab1986a6b2276de9c4b016b03dd9bc6eaf84a6e983fa59124c14f4df3bc9d828"
    },
    {
        "previous_block_hash": "ab1986a6b2276de9c4b016b03dd9bc6eaf84a6e983fa59124c14f4df3bc9d828",
        "time": "2024-07-14|15:39:04.665",
        "status": "Valide",
        "produit": "Fer",
        "current_place": "Chalons-en-Champagne",
        "destination": "Reims",
        "packages_total_number": "2",
        "packages_total_weight": "400kg",
        "package_id": "9729729713",
        "product_detail": "ceci est un test3",
        "product_family": "Metal",
        "product_current_owner": "Moi",
        "product_origin_country": "Africa",
        "product_origin_producer": "Jupiter",
        "block_hash": "2821359b93b604928a5e8dab17d2c6e3dbc85d62ed5a2d92e82fa40c9ea00089"
    },
    {
        "previous_block_hash": "2821359b93b604928a5e8dab17d2c6e3dbc85d62ed5a2d92e82fa40c9ea00089",
        "time": "2024-07-14|15:40:38.698",
        "status": "Valide",
        "produit": "Fer",
        "current_place": "Chalons-en-Champagne",
        "destination": "Reims",
        "packages_total_number": "2",
        "packages_total_weight": "400kg",
        "package_id": "9729729713",
        "product_detail": "ceci est un test3",
        "product_family": "Metal",
        "product_current_owner": "Moi",
        "product_origin_country": "Africa",
        "product_origin_producer": "Jupiter",
        "block_hash": "6859b1042ef8fd287e2a6f949bb18db599fa528661c68f6609bb58f76f377839"
    },
    {
        "previous_block_hash": "6859b1042ef8fd287e2a6f949bb18db599fa528661c68f6609bb58f76f377839",
        "time": "2024-07-14|15:41:16.411",
        "status": "Valide",
        "produit": "Fer",
        "current_place": "Chalons-en-Champagne",
        "destination": "Reims",
        "packages_total_number": "2",
        "packages_total_weight": "400kg",
        "package_id": "9729729713",
        "product_detail": "ceci est un test3",
        "product_family": "Metal",
        "product_current_owner": "Moi",
        "product_origin_country": "Africa",
        "product_origin_producer": "Jupiter",
        "block_hash": "6e9e57fe656bcca41eace17ae281c8c8417b439f3eb96b7b8055a6681c2dfc09"
    },
    {
        "previous_block_hash": "6e9e57fe656bcca41eace17ae281c8c8417b439f3eb96b7b8055a6681c2dfc09",
        "time": "2024-07-14|15:44:14.036",
        "status": "Valide",
        "produit": "Fer",
        "current_place": "Chalons-en-Champagne",
        "destination": "Reims",
        "packages_total_number": "2",
        "packages_total_weight": "400kg",
        "package_id": "9729729713",
        "product_detail": "ceci est un test3",
        "product_family": "Metal",
        "product_current_owner": "Moi",
        "product_origin_country": "Africa",
        "product_origin_producer": "Jupiter",
        "block_hash": "a25fb2dd101a9c1defb7d9d32b927e0bdd51d06ec656d3dc12c96d1ae0beb26a"
    },
    {
        "previous_block_hash": "a25fb2dd101a9c1defb7d9d32b927e0bdd51d06ec656d3dc12c96d1ae0beb26a",
        "time": "2024-07-14|15:45:44.968",
        "status": "Valide",
        "produit": "Fer",
        "current_place": "Chalons-en-Champagne",
        "destination": "Reims",
        "packages_total_number": "2",
        "packages_total_weight": "400kg",
        "package_id": "9729729713",
        "product_detail": "ceci est un test3",
        "product_family": "Metal",
        "product_current_owner": "Moi",
        "product_origin_country": "Africa",
        "product_origin_producer": "Jupiter",
        "block_hash": "3dc99cd3db013eb457d84ad5cc19286bbc0259e0b2f9488a65263130f3f3062d"
    },
    {
        "previous_block_hash": "3dc99cd3db013eb457d84ad5cc19286bbc0259e0b2f9488a65263130f3f3062d",
        "time": "2024-07-14|15:47:35.974",
        "status": "Valide",
        "produit": "Fer",
        "current_place": "Chalons-en-Champagne",
        "destination": "Reims",
        "packages_total_number": "2",
        "packages_total_weight": "400kg",
        "package_id": "9729729713",
        "product_detail": "ceci est un test3",
        "product_family": "Metal",
        "product_current_owner": "Moi",
        "product_origin_country": "Africa",
        "product_origin_producer": "Jupiter",
        "block_hash": "5d2d2e3d1b21f663c962b36fe4b80a363825a56271783ce9578f0f3ac41fe3ac"
    },
    {
        "previous_block_hash": "5d2d2e3d1b21f663c962b36fe4b80a363825a56271783ce9578f0f3ac41fe3ac",
        "time": "2024-07-14|15:47:52.068",
        "status": "Valide",
        "produit": "Fer",
        "current_place": "Chalons-en-Champagne",
        "destination": "Reims",
        "packages_total_number": "2",
        "packages_total_weight": "400kg",
        "package_id": "9729729713",
        "product_detail": "ceci est un test3",
        "product_family": "Metal",
        "product_current_owner": "Moi",
        "product_origin_country": "Africa",
        "product_origin_producer": "Jupiter",
        "block_hash": "3065388fd9d91dbd916ffefb12f788e70b4696796b08bc837783efc048de0566"
    },
    {
        "previous_block_hash": "3065388fd9d91dbd916ffefb12f788e70b4696796b08bc837783efc048de0566",
        "time": "2024-07-14|15:48:34.138",
        "status": "Valide",
        "produit": "Fer",
        "current_place": "Chalons-en-Champagne",
        "destination": "Reims",
        "packages_total_number": "2",
        "packages_total_weight": "400kg",
        "package_id": "9729729713",
        "product_detail": "ceci est un test3",
        "product_family": "Metal",
        "product_current_owner": "Moi",
        "product_origin_country": "Africa",
        "product_origin_producer": "Jupiter",
        "block_hash": "24ca19291720c8645ca4037ac398d92906e52ca90009fd4952acd169e35651a6"
    },
    {
        "previous_block_hash": "24ca19291720c8645ca4037ac398d92906e52ca90009fd4952acd169e35651a6",
        "time": "2024-07-14|15:50:59.817",
        "status": "Valide",
        "produit": "Fer",
        "current_place": "Chalons-en-Champagne",
        "destination": "Reims",
        "packages_total_number": "2",
        "packages_total_weight": "400kg",
        "package_id": "9729729713",
        "product_detail": "ceci est un test3",
        "product_family": "Metal",
        "product_current_owner": "Moi",
        "product_origin_country": "Africa",
        "product_origin_producer": "Jupiter",
        "block_hash": "70eba7fdef25ef87bf0cd4f315ee61c2296d19f7361ee737b5ba7f5615a24c75"
    },
    {
        "previous_block_hash": "70eba7fdef25ef87bf0cd4f315ee61c2296d19f7361ee737b5ba7f5615a24c75",
        "time": "2024-07-14|15:53:33.355",
        "status": "Valide",
        "product_name": "Fer",
        "product_location": "Chalons-en-Champagne",
        "product_destination": "Reims",
        "packages_total_number": "2",
        "packages_total_weight": "400kg",
        "package_id": "9729729713",
        "product_detail": "ceci est un test3",
        "product_family": "Metal",
        "product_current_owner": "Moi",
        "product_origin_country": "Africa",
        "product_origin_producer": "Jupiter",
        "block_hash": "bfb1e2fc5512e36e5a43691154f63b2ae29202cdc6ee0298300916925ddf84d0"
    },
    {
        "previous_block_hash": "bfb1e2fc5512e36e5a43691154f63b2ae29202cdc6ee0298300916925ddf84d0",
        "time": "2024-07-14|15:54:45.587",
        "status": "Valide",
        "product_name": "Fer",
        "product_location": "Chalons-en-Champagne",
        "product_destination": "Reims",
        "packages_total_number": "2",
        "packages_total_weight": "400kg",
        "package_id": "9729729713",
        "product_detail": "ceci est un test3",
        "product_family": "Metal",
        "product_current_owner": "Moi",
        "product_origin_country": "Africa",
        "product_origin_producer": "Jupiter",
        "block_hash": "45f8ca44618a487bbcab83c6d2ce5d12c029971f63d2a1c6a80a29cc4ef9a5e3"
    },
    {
        "previous_block_hash": "45f8ca44618a487bbcab83c6d2ce5d12c029971f63d2a1c6a80a29cc4ef9a5e3",
        "time": "2024-07-14|15:55:58.794",
        "status": "Valide",
        "product_name": "Fer",
        "product_location": "Chalons-en-Champagne",
        "product_destination": "Reims",
        "packages_total_number": "2",
        "packages_total_weight": "400kg",
        "package_id": "9729729713",
        "product_detail": "ceci est un test3",
        "product_family": "Metal",
        "product_current_owner": "Moi",
        "product_origin_country": "Africa",
        "product_origin_producer": "Jupiter",
        "block_hash": "96f277f54afab42102044f47b4c79a273c04c09dc47c4ced52291c260ed4c781"
    },
    {
        "previous_block_hash": "96f277f54afab42102044f47b4c79a273c04c09dc47c4ced52291c260ed4c781",
        "time": "2024-07-14|15:56:23.277",
        "status": "Valide",
        "product_name": "Fer",
        "product_location": "Chalons-en-Champagne",
        "product_destination": "Reims",
        "packages_total_number": "2",
        "packages_total_weight": "400kg",
        "package_id": "9729729713",
        "product_detail": "ceci est un test3",
        "product_family": "Metal",
        "product_current_owner": "Moi",
        "product_origin_country": "Africa",
        "product_origin_producer": "Jupiter",
        "block_hash": "d510dd464aaf442296e92dc2b65dcb9ab8c2c3f8092c718cdf4573eac863b701"
    },
    {
        "previous_block_hash": "d510dd464aaf442296e92dc2b65dcb9ab8c2c3f8092c718cdf4573eac863b701",
        "time": "2024-07-14|15:56:43.603",
        "status": "Valide",
        "product_name": "Fer",
        "product_location": "Chalons-en-Champagne",
        "product_destination": "Reims",
        "packages_total_number": "2",
        "packages_total_weight": "400kg",
        "package_id": "9729729713",
        "product_detail": "ceci est un test3",
        "product_family": "Metal",
        "product_current_owner": "Moi",
        "product_origin_country": "Africa",
        "product_origin_producer": "Jupiter",
        "block_hash": "2e9b33c07912fe97163d9fbe409276b755aa7b56fcb454d07a8e0cfcb28ab525"
    },
    {
        "previous_block_hash": "2e9b33c07912fe97163d9fbe409276b755aa7b56fcb454d07a8e0cfcb28ab525",
        "time": "2024-07-14|15:57:14.724",
        "status": "Valide",
        "product_name": "Fer",
        "product_location": "Chalons-en-Champagne",
        "product_destination": "Reims",
        "packages_total_number": "2",
        "packages_total_weight": "400kg",
        "package_id": "9729729713",
        "product_detail": "ceci est un test3",
        "product_family": "Metal",
        "product_current_owner": "Moi",
        "product_origin_country": "Africa",
        "product_origin_producer": "Jupiter",
        "block_hash": "b945a501f89323ac6e2f17f8960477be3a67d30ba5b8ee84b1051a1381eae975"
    },
    {
        "previous_block_hash": "b945a501f89323ac6e2f17f8960477be3a67d30ba5b8ee84b1051a1381eae975",
        "time": "2024-07-14|15:58:28.431",
        "status": "Valide",
        "product_name": "Fer",
        "product_location": "Chalons-en-Champagne",
        "product_destination": "Reims",
        "packages_total_number": "2",
        "packages_total_weight": "400kg",
        "package_id": "9729729713",
        "product_detail": "ceci est un test3",
        "product_family": "Metal",
        "product_current_owner": "Moi",
        "product_origin_country": "Africa",
        "product_origin_producer": "Jupiter",
        "block_hash": "dcaa23f3dec5080453c39ad18b48da40171ec44169a37f19f4dc45164e38631d"
    },
    {
        "previous_block_hash": "dcaa23f3dec5080453c39ad18b48da40171ec44169a37f19f4dc45164e38631d",
        "time": "2024-07-14|16:09:26.299",
        "status": "Valide",
        "product_name": "Fer",
        "product_location": "Chalons-en-Champagne",
        "product_destination": "Reims",
        "packages_total_number": "2",
        "packages_total_weight": "400kg",
        "package_id": "9729729713",
        "product_detail": "ceci est un test3",
        "product_family": "Metal",
        "product_current_owner": "Moi",
        "product_origin_country": "Africa",
        "product_origin_producer": "Jupiter",
        "block_hash": "66707c03237e768804ba01b9ff8a8fc4b4c250f0535d6122ed0def1712a886ef"
    },
    {
        "previous_block_hash": "66707c03237e768804ba01b9ff8a8fc4b4c250f0535d6122ed0def1712a886ef",
        "time": "2024-07-14|16:09:44.512",
        "status": "Valide",
        "product_name": "Fer",
        "product_location": "Chalons-en-Champagne",
        "product_destination": "Reims",
        "packages_total_number": "2",
        "packages_total_weight": "400kg",
        "package_id": "9729729713",
        "product_detail": "ceci est un test3",
        "product_family": "Metal",
        "product_current_owner": "Moi",
        "product_origin_country": "Africa",
        "product_origin_producer": "Jupiter",
        "block_hash": "370df49141e5da3a0b6ead332e82acef431702db10c772d159530fe4ab9d54c8"
    },
    {
        "previous_block_hash": "370df49141e5da3a0b6ead332e82acef431702db10c772d159530fe4ab9d54c8",
        "time": "2024-07-14|16:12:46.048",
        "status": "Valide",
        "product_name": "Fer",
        "product_location": "Chalons-en-Champagne",
        "product_destination": "Reims",
        "packages_total_number": "2",
        "packages_total_weight": "400kg",
        "package_id": "9729729713",
        "product_detail": "ceci est un test3",
        "product_family": "Metal",
        "product_current_owner": "Moi",
        "product_origin_country": "Africa",
        "product_origin_producer": "Jupiter",
        "block_hash": "619ad7b4524a4edaa49418b5335e7eaf6e9c120c17f23a2e22ae923564d473f5"
    },
    {
        "previous_block_hash": "619ad7b4524a4edaa49418b5335e7eaf6e9c120c17f23a2e22ae923564d473f5",
        "time": "2024-07-14|16:33:42.237",
        "status": "Valide",
        "product_name": "Fer",
        "product_location": "Chalons-en-Champagne",
        "product_destination": "Reims",
        "packages_total_number": "2",
        "packages_total_weight": "400kg",
        "package_id": "9729729713",
        "product_detail": "ceci est un test3",
        "product_family": "Metal",
        "product_current_owner": "Moi",
        "product_origin_country": "Africa",
        "product_origin_producer": "Jupiter",
        "block_hash": "c2ea48b02f3cb519ab01be1aa13d2a1d2f00c9a029cf9aa8c0b4a86ccbbc3d70"
    },
    {
        "previous_block_hash": "c2ea48b02f3cb519ab01be1aa13d2a1d2f00c9a029cf9aa8c0b4a86ccbbc3d70",
        "time": "2024-07-14|16:34:13.513",
        "status": "Valide",
        "product_name": "Fer",
        "product_location": "Chalons-en-Champagne",
        "product_destination": "Reims",
        "packages_total_number": "2",
        "packages_total_weight": "400kg",
        "package_id": "9729729713",
        "product_detail": "ceci est un test3",
        "product_family": "Metal",
        "product_current_owner": "Moi",
        "product_origin_country": "Africa",
        "product_origin_producer": "Jupiter",
        "block_hash": "7c5b62235c46f96b9930c029cd5fb280c364768cd7ec061889625051b4c285b4"
    },
    {
        "previous_block_hash": "7c5b62235c46f96b9930c029cd5fb280c364768cd7ec061889625051b4c285b4",
        "time": "2024-07-14|16:36:37.149",
        "status": "Valide",
        "product_name": "Fer",
        "product_location": "Chalons-en-Champagne",
        "product_destination": "Reims",
        "packages_total_number": "2",
        "packages_total_weight": "400kg",
        "package_id": "9729729713",
        "product_detail": "ceci est un test3",
        "product_family": "Metal",
        "product_current_owner": "Moi",
        "product_origin_country": "Africa",
        "product_origin_producer": "Jupiter",
        "block_hash": "38323e512ad2cce2c3973a2016eb1fc0e8fef2d499d3be87a0dcab92e46aebdc"
    },
    {
        "previous_block_hash": "38323e512ad2cce2c3973a2016eb1fc0e8fef2d499d3be87a0dcab92e46aebdc",
        "time": "2024-07-14|16:39:02.073",
        "status": "Valide",
        "product_name": "Fer",
        "product_location": "Chalons-en-Champagne",
        "product_destination": "Reims",
        "packages_total_number": "2",
        "packages_total_weight": "400kg",
        "package_id": "9729729713",
        "product_detail": "ceci est un test3",
        "product_family": "Metal",
        "product_current_owner": "Moi",
        "product_origin_country": "Africa",
        "product_origin_producer": "Jupiter",
        "block_hash": "edc22f3413d9f5685cc4bb6521ed0044c6bc4730e513f4f15d75896879c5f576"
    },
    {
        "previous_block_hash": "edc22f3413d9f5685cc4bb6521ed0044c6bc4730e513f4f15d75896879c5f576",
        "time": "2024-07-14|16:39:29.755",
        "status": "Valide",
        "product_name": "Fer",
        "product_location": "Chalons-en-Champagne",
        "product_destination": "Reims",
        "packages_total_number": "2",
        "packages_total_weight": "400kg",
        "package_id": "9729729713",
        "product_detail": "ceci est un test3",
        "product_family": "Metal",
        "product_current_owner": "Moi",
        "product_origin_country": "Africa",
        "product_origin_producer": "Jupiter",
        "block_hash": "c2e5acbc155215e225873f6ed0587d7f0b00e4294be9254e9de7e0e2dd4ee019"
    },
    {
        "previous_block_hash": "c2e5acbc155215e225873f6ed0587d7f0b00e4294be9254e9de7e0e2dd4ee019",
        "time": "2024-07-14|16:40:16.784",
        "status": "Valide",
        "product_name": "Fer",
        "product_location": "Chalons-en-Champagne",
        "product_destination": "Reims",
        "packages_total_number": "2",
        "packages_total_weight": "400kg",
        "package_id": "9729729713",
        "product_detail": "ceci est un test3",
        "product_family": "Metal",
        "product_current_owner": "Moi",
        "product_origin_country": "Africa",
        "product_origin_producer": "Jupiter",
        "block_hash": "c0eba1e34663491cf8774bbbb99a1e0cc6fac6b51f0a15e5594d0c3c256cb316"
    },
    {
        "previous_block_hash": "c0eba1e34663491cf8774bbbb99a1e0cc6fac6b51f0a15e5594d0c3c256cb316",
        "time": "2024-07-14|16:41:02.910",
        "status": "Valide",
        "product_name": "Fer",
        "product_location": "Chalons-en-Champagne",
        "product_destination": "Reims",
        "packages_total_number": "2",
        "packages_total_weight": "400kg",
        "package_id": "9729729713",
        "product_detail": "ceci est un test3",
        "product_family": "Metal",
        "product_current_owner": "Moi",
        "product_origin_country": "Africa",
        "product_origin_producer": "Jupiter",
        "block_hash": "5c84a6bf0494e056216b7d87788b3799859ad879a04d9d1c08cd1e6c7cbeb22d"
    },
    {
        "previous_block_hash": "5c84a6bf0494e056216b7d87788b3799859ad879a04d9d1c08cd1e6c7cbeb22d",
        "time": "2024-07-14|16:42:11.907",
        "status": "Valide",
        "product_name": "Fer",
        "product_location": "Chalons-en-Champagne",
        "product_destination": "Reims",
        "packages_total_number": "2",
        "packages_total_weight": "400kg",
        "package_id": "9729729713",
        "product_detail": "ceci est un test3",
        "product_family": "Metal",
        "product_current_owner": "Moi",
        "product_origin_country": "Africa",
        "product_origin_producer": "Jupiter",
        "block_hash": "e6f085e448fa71865e628c845d80bed301718705219a0b1bf4656aa7046ace0d"
    },
    {
        "previous_block_hash": "e6f085e448fa71865e628c845d80bed301718705219a0b1bf4656aa7046ace0d",
        "time": "2024-07-14|16:44:58.719",
        "status": "Valide",
        "product_name": "Fer",
        "product_location": "Chalons-en-Champagne",
        "product_destination": "Reims",
        "packages_total_number": "2",
        "packages_total_weight": "400kg",
        "package_id": "9729729713",
        "product_detail": "ceci est un test3",
        "product_family": "Metal",
        "product_current_owner": "Moi",
        "product_origin_country": "Africa",
        "product_origin_producer": "Jupiter",
        "block_hash": "991c63868c6fb300ece9cd92766727781d96e537c70ef7a4bb535913425001b4"
    },
    {
        "previous_block_hash": "991c63868c6fb300ece9cd92766727781d96e537c70ef7a4bb535913425001b4",
        "time": "2024-07-14|16:53:42.546",
        "status": "Valide",
        "product_name": "Fer",
        "product_location": "Chalons-en-Champagne",
        "product_destination": "Reims",
        "packages_total_number": "2",
        "packages_total_weight": "400kg",
        "package_id": "9729729713",
        "product_detail": "ceci est un test3",
        "product_family": "Metal",
        "product_current_owner": "Moi",
        "product_origin_country": "Africa",
        "product_origin_producer": "Jupiter",
        "block_hash": "a825e9dd026f8f5473650fc7e609e40212a32f568a287ea8d9612f87ba82d107"
    },
    {
        "previous_block_hash": "a825e9dd026f8f5473650fc7e609e40212a32f568a287ea8d9612f87ba82d107",
        "time": "2024-07-14|16:55:52.704",
        "status": "Valide",
        "product_name": "Fer",
        "product_location": "Chalons-en-Champagne",
        "product_destination": "Reims",
        "packages_total_number": "2",
        "packages_total_weight": "400kg",
        "package_id": "9729729713",
        "product_detail": "ceci est un test3",
        "product_family": "Metal",
        "product_current_owner": "Moi",
        "product_origin_country": "Africa",
        "product_origin_producer": "Jupiter",
        "block_hash": "7acf4ee133b0ae3a193914fe3105f65a2a2f35fe889429931540564a44af5616"
    },
    {
        "previous_block_hash": "7acf4ee133b0ae3a193914fe3105f65a2a2f35fe889429931540564a44af5616",
        "time": "2024-07-18|21:27:26.973",
        "status": "Valide",
        "product_name": "Fer",
        "product_location": "Chalons-en-Champagne",
        "product_destination": "Reims",
        "packages_total_number": "2",
        "packages_total_weight": "400kg",
        "package_id": "9729729713",
        "product_detail": "ceci est un test3",
        "product_family": "Metal",
        "product_current_owner": "Moi",
        "product_origin_country": "Africa",
        "product_origin_producer": "Jupiter",
        "block_hash": "1956bd3ec7d4716183ba53d9de019417961fcfd50170254d264696d7039dbd4b"
    },
    {
        "previous_block_hash": "1956bd3ec7d4716183ba53d9de019417961fcfd50170254d264696d7039dbd4b",
        "time": "2024-07-18|21:29:26.265",
        "status": "Valide",
        "product_name": "Fer",
        "product_location": "Chalons-en-Champagne",
        "product_destination": "Reims",
        "packages_total_number": "2",
        "packages_total_weight": "400kg",
        "package_id": "9729729713",
        "product_detail": "ceci est un test3",
        "product_family": "Metal",
        "product_current_owner": "Moi",
        "product_origin_country": "Africa",
        "product_origin_producer": "Jupiter",
        "block_hash": "d2d7d60585d892c8b917e8124046a6c095f59a004d9e8359f54ef937f0f59e95"
    },
    {
        "previous_block_hash": "d2d7d60585d892c8b917e8124046a6c095f59a004d9e8359f54ef937f0f59e95",
        "time": "2024-07-18|21:30:04.576",
        "status": "Valide",
        "product_name": "Fer",
        "product_location": "Chalons-en-Champagne",
        "product_destination": "Reims",
        "packages_total_number": "2",
        "packages_total_weight": "400kg",
        "package_id": "9729729713",
        "product_detail": "ceci est un test3",
        "product_family": "Metal",
        "product_current_owner": "Moi",
        "product_origin_country": "Africa",
        "product_origin_producer": "Jupiter",
        "block_hash": "aa6acbad49ac4e501e23c17d79558504fc5ee60fa87562840d8db34c3a57789b"
    },
    {
        "previous_block_hash": "aa6acbad49ac4e501e23c17d79558504fc5ee60fa87562840d8db34c3a57789b",
        "time": "2024-07-18|21:30:33.148",
        "status": "Valide",
        "product_name": "Fer",
        "product_location": "Chalons-en-Champagne",
        "product_destination": "Reims",
        "packages_total_number": "2",
        "packages_total_weight": "400kg",
        "package_id": "9729729713",
        "product_detail": "ceci est un test3",
        "product_family": "Metal",
        "product_current_owner": "Moi",
        "product_origin_country": "Africa",
        "product_origin_producer": "Jupiter",
        "block_hash": "3a3e7f06637186848a61e97c182cd7ac1a0f7d856088a709c327a49a58c3ec12"
    },
    {
        "previous_block_hash": "3a3e7f06637186848a61e97c182cd7ac1a0f7d856088a709c327a49a58c3ec12",
        "time": "2024-07-18|21:31:50.641",
        "status": "Valide",
        "product_name": "Fer",
        "product_location": "Chalons-en-Champagne",
        "product_destination": "Reims",
        "packages_total_number": "2",
        "packages_total_weight": "400kg",
        "package_id": "9729729713",
        "product_detail": "ceci est un test3",
        "product_family": "Metal",
        "product_current_owner": "Moi",
        "product_origin_country": "Africa",
        "product_origin_producer": "Jupiter",
        "block_hash": "3ffb16984b12f9e0214f6643559d01b8c615ef6ca18ecdcf0a366811860cb9b1"
    },
    {
        "previous_block_hash": "3ffb16984b12f9e0214f6643559d01b8c615ef6ca18ecdcf0a366811860cb9b1",
        "time": "2024-07-18|21:32:03.674",
        "status": "Valide",
        "product_name": "Fer",
        "product_location": "Chalons-en-Champagne",
        "product_destination": "Reims",
        "packages_total_number": "2",
        "packages_total_weight": "400kg",
        "package_id": "9729729713",
        "product_detail": "ceci est un test3",
        "product_family": "Metal",
        "product_current_owner": "Moi",
        "product_origin_country": "Africa",
        "product_origin_producer": "Jupiter",
        "block_hash": "a6e61028e9408d4baa9210e126e65f434559d89a5c7b085b04bc083a5b49e87d"
    },
    {
        "previous_block_hash": "a6e61028e9408d4baa9210e126e65f434559d89a5c7b085b04bc083a5b49e87d",
        "time": "2024-07-18|21:32:16.766",
        "status": "Valide",
        "product_name": "Fer",
        "product_location": "Chalons-en-Champagne",
        "product_destination": "Reims",
        "packages_total_number": "2",
        "packages_total_weight": "400kg",
        "package_id": "9729729713",
        "product_detail": "ceci est un test3",
        "product_family": "Metal",
        "product_current_owner": "Moi",
        "product_origin_country": "Africa",
        "product_origin_producer": "Jupiter",
        "block_hash": "c2ff6c9a6c1ea978a6fdeb429da45da31b06444ed7c040edec3a9db0fcde4349"
    },
    {
        "previous_block_hash": "c2ff6c9a6c1ea978a6fdeb429da45da31b06444ed7c040edec3a9db0fcde4349",
        "time": "2024-07-18|21:33:00.140",
        "status": "Valide",
        "product_name": "Fer",
        "product_location": "Chalons-en-Champagne",
        "product_destination": "Reims",
        "packages_total_number": "2",
        "packages_total_weight": "400kg",
        "package_id": "9729729713",
        "product_detail": "ceci est un test3",
        "product_family": "Metal",
        "product_current_owner": "Moi",
        "product_origin_country": "Africa",
        "product_origin_producer": "Jupiter",
        "block_hash": "4c8650d65c028809388bc4fa3669069df390c45e4cbcdbe9bf34895a4ba0b7d6"
    },
    {
        "previous_block_hash": "4c8650d65c028809388bc4fa3669069df390c45e4cbcdbe9bf34895a4ba0b7d6",
        "time": "2024-07-18|21:33:36.426",
        "status": "Valide",
        "product_name": "Fer",
        "product_location": "Chalons-en-Champagne",
        "product_destination": "Reims",
        "packages_total_number": "2",
        "packages_total_weight": "400kg",
        "package_id": "9729729713",
        "product_detail": "ceci est un test3",
        "product_family": "Metal",
        "product_current_owner": "Moi",
        "product_origin_country": "Africa",
        "product_origin_producer": "Jupiter",
        "block_hash": "19d249b0ca6a769c817e9365041b04b41a016dba89a2cea87fe4944ed4fa2148"
    },
    {
        "previous_block_hash": "19d249b0ca6a769c817e9365041b04b41a016dba89a2cea87fe4944ed4fa2148",
        "time": "2024-07-18|21:35:40.081",
        "status": "Valide",
        "product_name": "Fer",
        "product_location": "Chalons-en-Champagne",
        "product_destination": "Reims",
        "packages_total_number": "2",
        "packages_total_weight": "400kg",
        "package_id": "9729729713",
        "product_detail": "ceci est un test3",
        "product_family": "Metal",
        "product_current_owner": "Moi",
        "product_origin_country": "Africa",
        "product_origin_producer": "Jupiter",
        "block_hash": "cd26f1ae2aefd13ec9fde00efc44cbd382f64ed9d1800bb67819b6156acc4b9c"
    },
    {
        "previous_block_hash": "cd26f1ae2aefd13ec9fde00efc44cbd382f64ed9d1800bb67819b6156acc4b9c",
        "time": "2024-07-18|21:36:56.967",
        "status": "Valide",
        "product_name": "Fer",
        "product_location": "Chalons-en-Champagne",
        "product_destination": "Reims",
        "packages_total_number": "2",
        "packages_total_weight": "400kg",
        "package_id": "9729729713",
        "product_detail": "ceci est un test3",
        "product_family": "Metal",
        "product_current_owner": "Moi",
        "product_origin_country": "Africa",
        "product_origin_producer": "Jupiter",
        "block_hash": "4b688396f55df2867c6c13b19890021ed2c24edc064cbce37cecac877d32f043"
    },
    {
        "previous_block_hash": "4b688396f55df2867c6c13b19890021ed2c24edc064cbce37cecac877d32f043",
        "time": "2024-07-18|21:37:26.368",
        "status": "Valide",
        "product_name": "Fer",
        "product_location": "Chalons-en-Champagne",
        "product_destination": "Reims",
        "packages_total_number": "2",
        "packages_total_weight": "400kg",
        "package_id": "9729729713",
        "product_detail": "ceci est un test3",
        "product_family": "Metal",
        "product_current_owner": "Moi",
        "product_origin_country": "Africa",
        "product_origin_producer": "Jupiter",
        "block_hash": "e3fd49f787ac7b93ac8d3d009620afee21bc5d314fe32992f3e64aeb3d2980da"
    },
    {
        "previous_block_hash": "e3fd49f787ac7b93ac8d3d009620afee21bc5d314fe32992f3e64aeb3d2980da",
        "time": "2024-07-18|21:43:48.825",
        "status": "Valide",
        "product_name": "Fer",
        "product_location": "Chalons-en-Champagne",
        "product_destination": "Reims",
        "packages_total_number": "2",
        "packages_total_weight": "400kg",
        "package_id": "9729729713",
        "product_detail": "ceci est un test3",
        "product_family": "Metal",
        "product_current_owner": "Moi",
        "product_origin_country": "Africa",
        "product_origin_producer": "Jupiter",
        "block_hash": "a011c249c35c26a8d46815cf8104c562aee45b483cb655c59f9bf128563c9100"
    },
    {
        "previous_block_hash": "a011c249c35c26a8d46815cf8104c562aee45b483cb655c59f9bf128563c9100",
        "time": "2024-07-18|21:45:02.401",
        "status": "Valide",
        "product_name": "Fer",
        "product_location": "Chalons-en-Champagne",
        "product_destination": "Reims",
        "packages_total_number": "2",
        "packages_total_weight": "400kg",
        "package_id": "9729729713",
        "product_detail": "ceci est un test3",
        "product_family": "Metal",
        "product_current_owner": "Moi",
        "product_origin_country": "Africa",
        "product_origin_producer": "Jupiter",
        "block_hash": "6d16beb81aeffc74f5fbb8d8f8f6ceadea619de068b96b1c0a1e36b9c5bf43a6"
    },
    {
        "previous_block_hash": "6d16beb81aeffc74f5fbb8d8f8f6ceadea619de068b96b1c0a1e36b9c5bf43a6",
        "time": "2024-07-18|21:45:17.243",
        "status": "Valide",
        "product_name": "Fer",
        "product_location": "Chalons-en-Champagne",
        "product_destination": "Reims",
        "packages_total_number": "2",
        "packages_total_weight": "400kg",
        "package_id": "9729729713",
        "product_detail": "ceci est un test3",
        "product_family": "Metal",
        "product_current_owner": "Moi",
        "product_origin_country": "Africa",
        "product_origin_producer": "Jupiter",
        "block_hash": "6db6d3543ade2c4d27f45d64f04ae725531a5c1fd627378de625919dfb28f63d"
    },
    {
        "previous_block_hash": "6db6d3543ade2c4d27f45d64f04ae725531a5c1fd627378de625919dfb28f63d",
        "time": "2024-07-18|21:45:53.105",
        "status": "Valide",
        "product_name": "Fer",
        "product_location": "Chalons-en-Champagne",
        "product_destination": "Reims",
        "packages_total_number": "2",
        "packages_total_weight": "400kg",
        "package_id": "9729729713",
        "product_detail": "ceci est un test3",
        "product_family": "Metal",
        "product_current_owner": "Moi",
        "product_origin_country": "Africa",
        "product_origin_producer": "Jupiter",
        "block_hash": "002e1c19f791065b58d03763ec0a93034184f1a6215aab89f023f6cc71574b50"
    },
    {
        "previous_block_hash": "002e1c19f791065b58d03763ec0a93034184f1a6215aab89f023f6cc71574b50",
        "time": "2024-07-18|21:46:41.063",
        "status": "Valide",
        "product_name": "Fer",
        "product_location": "Chalons-en-Champagne",
        "product_destination": "Reims",
        "packages_total_number": "2",
        "packages_total_weight": "400kg",
        "package_id": "9729729713",
        "product_detail": "ceci est un test3",
        "product_family": "Metal",
        "product_current_owner": "Moi",
        "product_origin_country": "Africa",
        "product_origin_producer": "Jupiter",
        "block_hash": "e5e1535dd3090d83553abd2b3e05b23c70bf505bcaf454a6db31421608f68c46"
    },
    {
        "previous_block_hash": "e5e1535dd3090d83553abd2b3e05b23c70bf505bcaf454a6db31421608f68c46",
        "time": "2024-07-18|21:52:39.066",
        "status": "Valide",
        "product_name": "Fer",
        "product_location": "Chalons-en-Champagne",
        "product_destination": "Reims",
        "packages_total_number": "2",
        "packages_total_weight": "400kg",
        "package_id": "9729729713",
        "product_detail": "ceci est un test3",
        "product_family": "Metal",
        "product_current_owner": "Moi",
        "product_origin_country": "Africa",
        "product_origin_producer": "Jupiter",
        "block_hash": "6aa97340bfcdf3426ad0d0353810b62615e6e6596f6b7ee192d908965a53e185"
    },
    {
        "previous_block_hash": "6aa97340bfcdf3426ad0d0353810b62615e6e6596f6b7ee192d908965a53e185",
        "time": "2024-07-18|22:10:18.506",
        "status": "Valide",
        "product_name": "Fer",
        "product_location": "Chalons-en-Champagne",
        "product_destination": "Reims",
        "packages_total_number": "2",
        "packages_total_weight": "400kg",
        "package_id": "9729729713",
        "product_detail": "ceci est un test3",
        "product_family": "Metal",
        "product_current_owner": "Moi",
        "product_origin_country": "Africa",
        "product_origin_producer": "Jupiter",
        "block_hash": "79fde9432c31927bfba0c2d11ab13840b83e4cc12ecfee685955dbf2aa1f0edf"
    },
    {
        "previous_block_hash": "79fde9432c31927bfba0c2d11ab13840b83e4cc12ecfee685955dbf2aa1f0edf",
        "time": "2024-07-18|22:12:13.225",
        "status": "Valide",
        "product_name": "Fer",
        "product_location": "Chalons-en-Champagne",
        "product_destination": "Reims",
        "packages_total_number": "2",
        "packages_total_weight": "400kg",
        "package_id": "9729729713",
        "product_detail": "ceci est un test3",
        "product_family": "Metal",
        "product_current_owner": "Moi",
        "product_origin_country": "Africa",
        "product_origin_producer": "Jupiter",
        "block_hash": "7ca1f52c73dbcf6b2b4127d548e401ae21394fae1f429954ec7dd70c4625681e"
    },
    {
        "previous_block_hash": "7ca1f52c73dbcf6b2b4127d548e401ae21394fae1f429954ec7dd70c4625681e",
        "time": "2024-07-18|22:13:07.781",
        "status": "Valide",
        "product_name": "Fer",
        "product_location": "Chalons-en-Champagne",
        "product_destination": "Reims",
        "packages_total_number": "2",
        "packages_total_weight": "400kg",
        "package_id": "9729729713",
        "product_detail": "ceci est un test3",
        "product_family": "Metal",
        "product_current_owner": "Moi",
        "product_origin_country": "Africa",
        "product_origin_producer": "Jupiter",
        "block_hash": "dd5c95d23223ff003b13fd21d4352543a1ba74aecc56ad599419500fdaa3c93c"
    },
    {
        "previous_block_hash": "dd5c95d23223ff003b13fd21d4352543a1ba74aecc56ad599419500fdaa3c93c",
        "time": "2024-07-18|22:13:49.091",
        "status": "Valide",
        "product_name": "Fer",
        "product_location": "Chalons-en-Champagne",
        "product_destination": "Reims",
        "packages_total_number": "2",
        "packages_total_weight": "400kg",
        "package_id": "9729729713",
        "product_detail": "ceci est un test3",
        "product_family": "Metal",
        "product_current_owner": "Moi",
        "product_origin_country": "Africa",
        "product_origin_producer": "Jupiter",
        "block_hash": "dd8494d5642a1472845457f4912bfdca6c196274fb5f871473d3e0ab567a87df"
    },
    {
        "previous_block_hash": "dd8494d5642a1472845457f4912bfdca6c196274fb5f871473d3e0ab567a87df",
        "time": "2024-07-18|22:14:15.630",
        "status": "Valide",
        "product_name": "Fer",
        "product_location": "Chalons-en-Champagne",
        "product_destination": "Reims",
        "packages_total_number": "2",
        "packages_total_weight": "400kg",
        "package_id": "9729729713",
        "product_detail": "ceci est un test3",
        "product_family": "Metal",
        "product_current_owner": "Moi",
        "product_origin_country": "Africa",
        "product_origin_producer": "Jupiter",
        "block_hash": "a85be350070a2d41a9115961f937b4d79df7a84dbd1255dae177a933ac929693"
    },
    {
        "previous_block_hash": "a85be350070a2d41a9115961f937b4d79df7a84dbd1255dae177a933ac929693",
        "time": "2024-07-18|22:15:44.647",
        "status": "Valide",
        "product_name": "Fer",
        "product_location": "Chalons-en-Champagne",
        "product_destination": "Reims",
        "packages_total_number": "2",
        "packages_total_weight": "400kg",
        "package_id": "9729729713",
        "product_detail": "ceci est un test3",
        "product_family": "Metal",
        "product_current_owner": "Moi",
        "product_origin_country": "Africa",
        "product_origin_producer": "Jupiter",
        "block_hash": "9d8660ec8a79051da3d785492e6a066f025221186196d12919e5ef53be443c2e"
    },
    {
        "previous_block_hash": "9d8660ec8a79051da3d785492e6a066f025221186196d12919e5ef53be443c2e",
        "time": "2024-07-18|22:19:35.415",
        "status": "Valide",
        "product_name": "Fer",
        "product_location": "Chalons-en-Champagne",
        "product_destination": "Reims",
        "packages_total_number": "2",
        "packages_total_weight": "400kg",
        "package_id": "9729729713",
        "product_detail": "ceci est un test3",
        "product_family": "Metal",
        "product_current_owner": "Moi",
        "product_origin_country": "Africa",
        "product_origin_producer": "Jupiter",
        "block_hash": "3ef04adab59ce763645491f98b3ba85e9ffd337b13509599bc35369b9fcfcca1"
    },
    {
        "previous_block_hash": "3ef04adab59ce763645491f98b3ba85e9ffd337b13509599bc35369b9fcfcca1",
        "time": "2024-07-18|22:21:06.550",
        "status": "Valide",
        "product_name": "Fer",
        "product_location": "Chalons-en-Champagne",
        "product_destination": "Reims",
        "packages_total_number": "2",
        "packages_total_weight": "400kg",
        "package_id": "9729729713",
        "product_detail": "ceci est un test3",
        "product_family": "Metal",
        "product_current_owner": "Moi",
        "product_origin_country": "Africa",
        "product_origin_producer": "Jupiter",
        "block_hash": "e643c239b4844a4af291bc216883b00fc2edf77a7cc5289f820c53f0a76e38b4"
    },
    {
        "previous_block_hash": "e643c239b4844a4af291bc216883b00fc2edf77a7cc5289f820c53f0a76e38b4",
        "time": "2024-07-18|22:22:32.879",
        "status": "Valide",
        "product_name": "Fer",
        "product_location": "Chalons-en-Champagne",
        "product_destination": "Reims",
        "packages_total_number": "2",
        "packages_total_weight": "400kg",
        "package_id": "9729729713",
        "product_detail": "ceci est un test3",
        "product_family": "Metal",
        "product_current_owner": "Moi",
        "product_origin_country": "Africa",
        "product_origin_producer": "Jupiter",
        "block_hash": "c4f4b4b7662b0c2315497638e544deee1f9a428a477f56d763db3e31b2b61639"
    }
]